[
    {
        "id": 1,
        "trace_id": "58d3:e374:5715:966a:c7b6:8fd3:1aae:79d6/26",
        "section": "Jetta",
        "customer_name": "Amalita",
        "mobile_no": "801-984-3842",
        "email": "agarlett0@amazon.de",
        "updated_at": "5/2/2023",
        "action": "Pendiqing"
    },
    {
        "id": 2,
        "trace_id": "14f6:4a6a:b1f8:5eaa:447e:20ec:bdfe:6443/59",
        "section": "XJ Series",
        "customer_name": "Mallory",
        "mobile_no": "761-468-6397",
        "email": "mkurth1@hp.com",
        "updated_at": "9/17/2023",
        "action": "Stavyshche"
    }
]